Workbook

Sheet ランキング100
A1: みんなの「困った」× 今すぐできる自動化 ランキング100
A2: 合計点 ＝ 困っている人の多さ×2 ＋ 自動化のしやすさ ＋ 案内できる広告・サービス。点数（1〜5）は青い数字で、変えると順位と記事の回が自動で入れ替わります。
A4: 順位 | B4: 困りごと | C4: 分野 | D4: 今のやり方 | E4: 自動化の方法 | F4: 道具の例 | G4: 困っている人の多さ | H4: 自動化のしやすさ | I4: 案内できる広告・サービス | J4: 合計点 | K4: 記事の回（1日3つ） | L4: 広告のジャンル | M4: 広告の状況 | N4: 根拠
A5: =RANK(J5,$J$5:$J$104)+COUNTIF($J$5:J5,J5)-1 | B5: 仕訳入力・帳簿付け | C5: 経理・事務 | D5: 通帳を見て手入力 | E5: 会計ソフトに銀行・カードをつないで自動仕訳 | F5: 会計ソフト | G5: 5 | H5: 5 | I5: 5 | J5: =G5*2+H5+I5 | K5: =ROUNDUP(A5/3,0) | L5: 会計ソフト | M5: 申請候補 | N5: 調査あり⑤
A6: =RANK(J6,$J$5:$J$104)+COUNTIF($J$5:J6,J6)-1 | B6: 請求書の作成・送付 | C6: 経理・事務 | D6: 毎月Excelで作って郵送 | E6: 請求書ソフトで毎月自動作成・送付 | F6: 請求書ソフト | G6: 5 | H6: 5 | I6: 5 | J6: =G6*2+H6+I6 | K6: =ROUNDUP(A6/3,0) | L6: 会計・請求書ソフト | M6: 申請候補 | N6: 推定
A7: =RANK(J7,$J$5:$J$104)+COUNTIF($J$5:J7,J7)-1 | B7: 毎日の献立を考える | C7: 家事 | D7: 毎日その場で考える | E7: 冷蔵庫の中身と家族の好みをAIに伝え、1週間分の献立と買い物リストを作らせる | F7: ChatGPT・Claude、献立アプリ | G7: 5 | H7: 5 | I7: 4 | J7: =G7*2+H7+I7 | K7: =ROUNDUP(A7/3,0) | L7: 宅配食・ミールキット | M7: 提携済み | N7: 調査あり①
A8: =RANK(J8,$J$5:$J$104)+COUNTIF($J$5:J8,J8)-1 | B8: 料理の下ごしらえと調理 | C8: 家事 | D8: 毎日手作業 | E8: ミールキットや宅配食に置き換え、自動調理鍋で放置調理にする | F8: 宅配食、自動調理鍋 | G8: 5 | H8: 4 | I8: 5 | J8: =G8*2+H8+I8 | K8: =ROUNDUP(A8/3,0) | L8: 宅配食・調理家電 | M8: 提携済み | N8: 調査あり②
A9: =RANK(J9,$J$5:$J$104)+COUNTIF($J$5:J9,J9)-1 | B9: 掃除機がけ | C9: 家事 | D9: 毎日手で | E9: ロボット掃除機に毎日決まった時刻で任せる | F9: ロボット掃除機 | G9: 5 | H9: 5 | I9: 4 | J9: =G9*2+H9+I9 | K9: =ROUNDUP(A9/3,0) | L9: 生活家電（楽天） | M9: 楽天で可 | N9: 調査あり②
A10: =RANK(J10,$J$5:$J$104)+COUNTIF($J$5:J10,J10)-1 | B10: 皿洗い | C10: 家事 | D10: 毎食後に手洗い | E10: 食洗機に入れるだけにする | F10: 食洗機 | G10: 5 | H10: 5 | I10: 4 | J10: =G10*2+H10+I10 | K10: =ROUNDUP(A10/3,0) | L10: 生活家電（楽天） | M10: 楽天で可 | N10: 調査あり③
A11: =RANK(J11,$J$5:$J$104)+COUNTIF($J$5:J11,J11)-1 | B11: 家計簿が続かない | C11: お金 | D11: レシートを手で入力 | E11: 家計簿アプリに口座とカードをつないで自動記帳 | F11: 家計簿アプリ | G11: 5 | H11: 5 | I11: 4 | J11: =G11*2+H11+I11 | K11: =ROUNDUP(A11/3,0) | L11: 家計簿アプリ | M11: 申請候補 | N11: 推定
A12: =RANK(J12,$J$5:$J$104)+COUNTIF($J$5:J12,J12)-1 | B12: 会議の議事録 | C12: 会社員 | D12: 聞きながら手で書く | E12: 文字起こしAIで録音から議事録まで自動作成 | F12: 文字起こしAI | G12: 5 | H12: 5 | I12: 4 | J12: =G12*2+H12+I12 | K12: =ROUNDUP(A12/3,0) | L12: 文字起こしツール | M12: 申請候補 | N12: 推定
A13: =RANK(J13,$J$5:$J$104)+COUNTIF($J$5:J13,J13)-1 | B13: 経費精算 | C13: 会社員 | D13: 領収書を貼って手入力 | E13: 領収書をスマホで撮るだけで読み取り・申請 | F13: 経費精算ソフト | G13: 5 | H13: 4 | I13: 5 | J13: =G13*2+H13+I13 | K13: =ROUNDUP(A13/3,0) | L13: 会計・経費精算ソフト | M13: 申請候補 | N13: 調査あり⑤
A14: =RANK(J14,$J$5:$J$104)+COUNTIF($J$5:J14,J14)-1 | B14: 確定申告（事業） | C14: 個人事業主 | D14: 年度末に1年分まとめて | E14: 日々の自動記帳から申告書まで会計ソフトで作る | F14: 会計ソフト | G14: 5 | H14: 4 | I14: 5 | J14: =G14*2+H14+I14 | K14: =ROUNDUP(A14/3,0) | L14: 会計ソフト | M14: 申請候補 | N14: 調査あり⑥
A15: =RANK(J15,$J$5:$J$104)+COUNTIF($J$5:J15,J15)-1 | B15: 予約電話の対応 | C15: 飲食店 | D15: 営業中に手を止めて出る | E15: ネット予約と電話の自動応答で電話そのものを減らす | F15: ネット予約、電話自動応答 | G15: 5 | H15: 5 | I15: 4 | J15: =G15*2+H15+I15 | K15: =ROUNDUP(A15/3,0) | L15: 予約システム・電話自動応答 | M15: 申請候補 | N15: 調査あり⑦
A16: =RANK(J16,$J$5:$J$104)+COUNTIF($J$5:J16,J16)-1 | B16: 予約管理・ダブルブッキング | C16: 美容室・サロン | D16: 紙の台帳と電話 | E16: ネット予約システムで24時間受付 | F16: 予約システム | G16: 5 | H16: 5 | I16: 4 | J16: =G16*2+H16+I16 | K16: =ROUNDUP(A16/3,0) | L16: 予約システム | M16: 申請候補 | N16: 推定
... A104: =RANK(J104,$J$5:$J$104)+COUNTIF($J$5:J104,J104)-1 | B104: 送迎ルートの作成 | C104: 介護 | D104: 毎日手で組む | E104: 利用者の住所から自動でルート作成 | F104: 送迎管理ソフト | G104: 3 | H104: 3 | I104: 2 | J104: =G104*2+H104+I104 | K104: =ROUNDUP(A104/3,0) | L104: なし | M104: — | N104: 推定

Sheet 広告の状況
A1: 自動化記事で案内できる広告の状況
A3: 状況 | B3: 件数 | C3: 意味
A4: 提携済み | B4: =COUNTIF('ランキング100'!M5:M104,"提携済み") | C4: A8で提携済みのジャンル（宅配食・家事代行・クリーニング・買取・講座・レンタル）。すぐ案内できる
A5: 楽天で可 | B5: =COUNTIF('ランキング100'!M5:M104,"楽天で可") | C5: 家電・日用品などは楽天アフィリエイトで案内できる
A6: 申請候補 | B6: =COUNTIF('ランキング100'!M5:M104,"申請候補") | C6: 会計ソフト・予約システム・勤怠など。A8で探して提携申請が必要（未確保）
A7: 要確認 | B7: =COUNTIF('ランキング100'!M5:M104,"要確認") | C7: 動画配信・音楽配信。提携しているか確認が必要
A8: 自社 | B8: =COUNTIF('ランキング100'!M5:M104,"自社") | C8: オリシャン開業パッケージへ誘導
A9: —（広告なし） | B9: =COUNTIF('ランキング100'!M5:M104,"—") | C9: 広告はなし。アクトシステムズ（システム開発）への相談に誘導する枠
A10: 合計 | B10: =SUM(B4:B9)

Sheet 調査の根拠
A1: 根拠にした調査（「推定」はAIの判断）
A3: 番号 | B3: 内容 | C3: 出典
A4: ① | B4: 名もなき家事で最もストレスなのは「献立を考える」68.4%、2位は排水口のゴミ取り、3位は衣類の整理 | C4: ワンコンパス調査（2019） https://resemom.jp/release/prtimes/20190919/56681.html
A5: ② | B5: 面倒くさい家事ランキング：1位料理、2位洗濯物を干す、3位お風呂掃除。以下、掃除機がけ・洗濯物をたたむ・詰め替えなど | C5: さぶろぐ調査（2022） https://www.kobe-np.co.jp/rentoku/omoshiro/202202/sp/0015050200.shtml
A6: ③ | B6: 後回しにしたい家事の上位に食器洗い | C6: さぶろぐ調査 https://news.allabout.co.jp/articles/o/38224/
A7: ④ | B7: 面倒な家事の1位はキッチン換気扇やコンロ掃除（500人） | C7: All About https://allabout.co.jp/gm/gc/489846/
A8: ⑤ | B8: 中小企業の経理の困りごと：1位は伝票・帳簿・仕訳入力、経費精算と給与計算も多い（362人） | C8: 日経クロステック Active https://active.nikkeibp.co.jp/atcl/wp/b/25/03/17/05339/
A9: ⑥ | B9: 個人事業主のストレス1位は「納税や確定申告」70.7%（600人） | C9: J-CAST（アメックス調査2023） https://www.j-cast.com/kaisha/2023/03/08457439.html
A10: ⑦ | B10: 飲食店経営者の60.8%が月200時間以上労働。原因にアナログな事務作業 | C10: 飲食店ドットコム（2026年1月） https://www.inshokuten.com/foodist/article/8206/
A11: ⑧ | B11: 小規模事業者の34%が在庫管理を課題に挙げる | C11: HandiFox 2026調査
A12: ⑨ | B12: note「#自動化したいこと」応募作品（note投稿・情報収集・ファイル整理・ケアマネの書類・番組検索・数字の記録など） | C12: https://note.com/tag/manus
A13: ⑩ | B13: レンタルサーバーのアフィリエイト報酬例：5,000〜10,000円/件 | C13: エックスサーバー https://www.xserver.ne.jp/feature/affiliate.php
A14: ⑪ | B14: 介護職員の不足と書類業務の簡素化が課題 | C14: なんじょう苑グループ調査 https://ryukyushimpo.jp/prtimes/entry-5191050.html
... A16: 自社の実例 | B16: スコヤホーム（点検カルテ・見積）、tabletto（レジ・モバイルオーダー）、不動産の問い合わせ受付、オリシャン | C16: 実際に作ったもの・提案したもの
